{
  "version": "wrk:2",
  "settings": {
    "wrk_binary": "wrk",
    "wrk_concurrency": 1,
    "wrk_connections": 60,
    "warmup_seconds": 15,
    "benchmark_seconds": 120,
    "wrk_script_location": "./final_report.lua",
    "before_worker_cmd": "rvm use 2.4.5 && bundle",
    "ruby_change_cmd": "bash -l -c \"rvm use 2.4.5 && bundle && ruby /home/ubuntu/rsb/wrk_runner.rb /tmp/benchlib_2085.json\"",
    "json_filename": "/tmp/benchlib_2085.json",
    "wrk_runner": "/home/ubuntu/rsb/wrk_runner.rb",
    "rack_env": "production",
    "bundle_gemfile": "Gemfile.2.4.5",
    "bundler_version": "1.17.3",
    "extra_env": {
      "RSB_EXTRA_GEMFILES": "Gemfile.puma",
      "RSB_RUN_INDEX": 10
    },
    "port": 4321,
    "timestamp": 1555068730,
    "url": "http://127.0.0.1:4321/static",
    "out_file": "/home/ubuntu/rsb/data/rsb_rack_1555068730.json",
    "verbose": 1,
    "server_cmd": "bundle exec puma -p 4321 -t 1:1 -w 1 --tag puma_rsb_rack_2085",
    "server_pre_cmd": "bundle",
    "server_kill_command": null,
    "server_kill_matcher": "puma_rsb_rack_2085",
    "suppress_server_output": true
  },
  "environment": {
    "RUBY_VERSION": "2.4.5",
    "RUBY_DESCRIPTION": "ruby 2.4.5p335 (2018-10-18 revision 65137) [x86_64-linux]",
    "rvm current": "ruby-2.4.5",
    "repo git sha": "7b147e97b2adc2976a38f44b0c0ad87c40f4e7d4",
    "repo status": "On branch master\nYour branch is up-to-date with 'origin/master'.\nChanges not staged for commit:\n  (use \"git add <file>...\" to update what will be committed)\n  (use \"git checkout -- <file>...\" to discard changes in working directory)\n\n\tmodified:   rack_test_app/Gemfile.2.0.0-p0.lock\n\tmodified:   rack_test_app/Gemfile.2.0.0-p648.lock\n\tmodified:   rack_test_app/Gemfile.2.1.10.lock\n\tmodified:   rack_test_app/Gemfile.2.2.10.lock\n\tmodified:   rack_test_app/Gemfile.2.3.8.lock\n\tmodified:   rack_test_app/Gemfile.2.4.5.lock\n\tmodified:   rack_test_app/Gemfile.2.5.3.lock\n\tmodified:   rack_test_app/Gemfile.2.6.0.lock\n\tmodified:   rails_test_app/Gemfile.2.0.0-p0.lock\n\tmodified:   rails_test_app/Gemfile.2.0.0-p648.lock\n\tmodified:   rails_test_app/Gemfile.2.1.10.lock\n\tmodified:   rails_test_app/Gemfile.2.2.10.lock\n\tmodified:   rails_test_app/Gemfile.2.3.8.lock\n\tmodified:   rails_test_app/Gemfile.2.4.5.lock\n\tmodified:   rails_test_app/Gemfile.2.5.3.lock\n\tmodified:   rails_test_app/Gemfile.2.6.0.lock\n\nUntracked files:\n  (use \"git add <file>...\" to include in what will be committed)\n\n\tcmd_file.sh\n\tnohup.out\n\nno changes added to commit (use \"git add\" and/or \"git commit -a\")\n",
    "uname": "Linux ip-172-31-52-148 4.4.0-1049-aws #58-Ubuntu SMP Fri Jan 12 23:17:09 UTC 2018 x86_64 x86_64 x86_64 GNU/Linux\n",
    "dir": "/home/ubuntu/rsb/rack_test_app",
    "env-LD_PRELOAD": null,
    "env-GEM_HOME": "/home/ubuntu/.rvm/gems/ruby-2.4.5",
    "env-RSB_EXTRA_GEMFILES": "Gemfile.puma",
    "env-RSB_DURATION": "120",
    "env-MY_RUBY_HOME": "/home/ubuntu/.rvm/rubies/ruby-2.4.5",
    "env-RSB_APP_SERVER": "puma",
    "env-RSB_PUMA_THREADS": "1",
    "env-RSB_WARMUP": "15",
    "env-BUNDLE_GEMFILE": "Gemfile.2.4.5",
    "env-RSB_RUN_INDEX": "10",
    "env-rvm_ruby_string": "ruby-2.4.5",
    "env-GEM_PATH": "/home/ubuntu/.rvm/gems/ruby-2.4.5:/home/ubuntu/.rvm/gems/ruby-2.4.5@global",
    "env-RSB_PUMA_PROCESSES": "1",
    "env-RSB_NUM_RUNS": "10",
    "env-RUBY_VERSION": "ruby-2.4.5",
    "env-BUNDLER_ORIG_BUNDLE_GEMFILE": "Gemfile.2.4.5",
    "env-BUNDLER_ORIG_GEM_HOME": "/home/ubuntu/.rvm/gems/ruby-2.4.5",
    "env-BUNDLER_ORIG_GEM_PATH": "/home/ubuntu/.rvm/gems/ruby-2.4.5:/home/ubuntu/.rvm/gems/ruby-2.4.5@global",
    "env-BUNDLER_ORIG_RUBYLIB": "BUNDLER_ENVIRONMENT_PRESERVER_INTENTIONALLY_NIL",
    "env-BUNDLER_ORIG_RUBYOPT": "BUNDLER_ENVIRONMENT_PRESERVER_INTENTIONALLY_NIL",
    "wrk_path": "/usr/local/bin/wrk\n"
  },
  "requests": {
    "warmup": {
      "latencies": [
        52,
        1,
        53,
        1,
        55,
        11,
        56,
        51,
        57,
        131,
        58,
        201,
        59,
        452,
        60,
        473,
        61,
        333,
        62,
        173,
        63,
        103,
        64,
        165,
        65,
        260,
        66,
        376,
        67,
        265,
        68,
        251,
        69,
        367,
        70,
        209,
        71,
        132,
        72,
        340,
        73,
        571,
        74,
        732,
        75,
        4631,
        76,
        21525,
        77,
        22976,
        78,
        40000,
        79,
        34842,
        80,
        11756,
        81,
        7656,
        82,
        5113,
        83,
        4342,
        84,
        3578,
        85,
        2953,
        86,
        2712,
        87,
        2123,
        88,
        2345,
        89,
        2667,
        90,
        2623,
        91,
        2254,
        92,
        1437,
        93,
        606,
        94,
        235,
        95,
        95,
        96,
        41,
        97,
        24,
        98,
        20,
        99,
        20,
        100,
        10,
        101,
        10,
        102,
        7,
        103,
        8,
        104,
        7,
        105,
        2,
        106,
        6,
        107,
        9,
        108,
        6,
        109,
        2,
        110,
        5,
        111,
        3,
        112,
        4,
        113,
        6,
        114,
        4,
        115,
        3,
        116,
        2,
        117,
        8,
        118,
        1,
        119,
        4,
        120,
        2,
        121,
        1,
        122,
        2,
        123,
        3,
        124,
        2,
        125,
        2,
        126,
        1,
        127,
        1,
        131,
        3,
        132,
        1,
        134,
        1,
        137,
        2,
        139,
        1,
        141,
        1,
        142,
        1,
        143,
        1,
        146,
        1,
        149,
        1,
        151,
        2,
        163,
        1,
        166,
        1,
        179,
        1,
        181,
        1,
        184,
        1,
        186,
        1,
        199,
        1,
        201,
        1,
        202,
        1,
        203,
        3,
        204,
        1,
        205,
        2,
        206,
        2,
        207,
        3,
        208,
        5,
        209,
        7,
        210,
        2,
        211,
        4,
        212,
        4,
        213,
        2,
        214,
        2,
        215,
        2,
        216,
        2,
        218,
        1,
        219,
        4,
        222,
        1,
        227,
        2,
        228,
        5,
        229,
        5,
        230,
        6,
        231,
        6,
        232,
        8,
        233,
        16,
        234,
        19,
        235,
        15,
        236,
        28,
        237,
        21,
        238,
        23,
        239,
        20,
        240,
        23,
        241,
        26,
        242,
        20,
        243,
        13,
        244,
        9,
        245,
        9,
        246,
        7,
        247,
        7,
        248,
        3,
        249,
        1,
        250,
        3,
        252,
        1,
        253,
        2,
        254,
        2,
        259,
        3,
        260,
        2,
        261,
        1,
        262,
        2,
        263,
        2,
        264,
        2,
        265,
        1,
        266,
        1,
        269,
        1,
        272,
        1,
        277,
        1,
        306,
        1,
        310,
        1,
        316,
        1,
        383,
        1,
        974,
        1,
        1040,
        1,
        8091,
        1,
        13019,
        1,
        17947,
        1,
        22875,
        1
      ],
      "req_per_sec": [
        8656,
        1,
        11686,
        1,
        12090,
        1,
        12100,
        1,
        12120,
        4,
        12130,
        1,
        12150,
        1,
        12160,
        7,
        12170,
        6,
        12180,
        9,
        12190,
        6,
        12200,
        1,
        12210,
        3,
        12212,
        1,
        12220,
        3,
        12230,
        7,
        12232,
        2,
        12240,
        3,
        12242,
        2,
        12250,
        2,
        12252,
        3,
        12260,
        5,
        12262,
        6,
        12270,
        2,
        12272,
        6,
        12280,
        1,
        12282,
        7,
        12290,
        3,
        12292,
        3,
        12303,
        8,
        12310,
        1,
        12313,
        5,
        12320,
        1,
        12323,
        2,
        12330,
        1,
        12333,
        5,
        12343,
        4,
        12353,
        1,
        12363,
        1,
        12373,
        3,
        12380,
        1,
        12383,
        4,
        12393,
        2,
        12404,
        3,
        12414,
        1,
        12424,
        2,
        12450,
        1,
        12464,
        1,
        12474,
        1,
        12484,
        1,
        12505,
        1,
        12525,
        2
      ],
      "errors": {
        "connect": 0,
        "read": 0,
        "write": 0,
        "status": 0,
        "timeout": 0
      }
    },
    "benchmark": {
      "latencies": [
        52,
        1,
        53,
        10,
        54,
        16,
        55,
        93,
        56,
        377,
        57,
        869,
        58,
        1513,
        59,
        2120,
        60,
        3008,
        61,
        2593,
        62,
        1672,
        63,
        1278,
        64,
        1416,
        65,
        1859,
        66,
        2149,
        67,
        2335,
        68,
        2542,
        69,
        2861,
        70,
        2281,
        71,
        1824,
        72,
        2737,
        73,
        4323,
        74,
        9058,
        75,
        54910,
        76,
        158939,
        77,
        189771,
        78,
        310787,
        79,
        187508,
        80,
        75681,
        81,
        51982,
        82,
        49313,
        83,
        80350,
        84,
        54613,
        85,
        31180,
        86,
        27080,
        87,
        22623,
        88,
        22124,
        89,
        21823,
        90,
        20322,
        91,
        17629,
        92,
        11417,
        93,
        5948,
        94,
        4076,
        95,
        3107,
        96,
        2725,
        97,
        1823,
        98,
        809,
        99,
        367,
        100,
        148,
        101,
        65,
        102,
        48,
        103,
        29,
        104,
        34,
        105,
        30,
        106,
        43,
        107,
        21,
        108,
        17,
        109,
        8,
        110,
        10,
        111,
        13,
        112,
        14,
        113,
        5,
        114,
        4,
        115,
        3,
        116,
        4,
        117,
        10,
        118,
        3,
        119,
        8,
        120,
        5,
        121,
        2,
        122,
        4,
        123,
        4,
        124,
        4,
        125,
        5,
        126,
        5,
        127,
        4,
        128,
        3,
        129,
        4,
        130,
        1,
        131,
        2,
        132,
        2,
        133,
        3,
        134,
        2,
        135,
        2,
        136,
        2,
        137,
        2,
        140,
        2,
        141,
        3,
        142,
        1,
        143,
        3,
        144,
        3,
        145,
        1,
        147,
        1,
        148,
        3,
        155,
        1,
        156,
        1,
        159,
        1,
        162,
        1,
        164,
        1,
        167,
        1,
        168,
        1,
        169,
        1,
        171,
        1,
        197,
        1,
        198,
        3,
        199,
        5,
        200,
        8,
        201,
        19,
        202,
        25,
        203,
        17,
        204,
        18,
        205,
        33,
        206,
        37,
        207,
        30,
        208,
        30,
        209,
        27,
        210,
        32,
        211,
        44,
        212,
        25,
        213,
        25,
        214,
        14,
        215,
        16,
        216,
        13,
        217,
        9,
        218,
        14,
        219,
        7,
        220,
        5,
        221,
        4,
        222,
        6,
        223,
        7,
        224,
        10,
        225,
        15,
        226,
        21,
        227,
        30,
        228,
        46,
        229,
        64,
        230,
        89,
        231,
        122,
        232,
        130,
        233,
        148,
        234,
        167,
        235,
        175,
        236,
        158,
        237,
        203,
        238,
        186,
        239,
        171,
        240,
        181,
        241,
        151,
        242,
        109,
        243,
        112,
        244,
        69,
        245,
        65,
        246,
        57,
        247,
        43,
        248,
        24,
        249,
        23,
        250,
        21,
        251,
        21,
        252,
        17,
        253,
        20,
        254,
        9,
        255,
        8,
        256,
        6,
        257,
        11,
        258,
        12,
        259,
        6,
        260,
        6,
        261,
        4,
        262,
        6,
        263,
        7,
        264,
        5,
        265,
        2,
        266,
        4,
        267,
        4,
        268,
        1,
        269,
        1,
        270,
        1,
        271,
        2,
        273,
        1,
        274,
        1,
        276,
        1,
        279,
        1,
        284,
        1,
        285,
        1,
        286,
        1,
        287,
        1,
        290,
        1,
        292,
        1,
        294,
        1,
        295,
        1,
        297,
        1,
        298,
        2,
        302,
        2,
        303,
        2,
        304,
        1,
        305,
        1,
        306,
        1,
        308,
        1,
        309,
        1,
        311,
        3,
        312,
        3,
        313,
        3,
        314,
        2,
        315,
        2,
        316,
        1,
        318,
        2,
        321,
        1,
        323,
        1,
        324,
        1,
        325,
        4,
        326,
        1,
        327,
        1,
        329,
        1,
        330,
        2,
        331,
        2,
        334,
        2,
        335,
        1,
        337,
        1,
        340,
        1,
        344,
        1,
        345,
        2,
        353,
        1,
        355,
        1,
        358,
        1,
        370,
        1,
        402,
        1,
        562,
        1,
        593,
        1,
        1151,
        1
      ],
      "req_per_sec": [
        11250,
        1,
        11530,
        1,
        11560,
        1,
        11570,
        3,
        11580,
        7,
        11590,
        3,
        11600,
        9,
        11610,
        9,
        11620,
        10,
        11630,
        9,
        11640,
        13,
        11650,
        5,
        11660,
        6,
        11666,
        1,
        11670,
        6,
        11676,
        1,
        11680,
        2,
        11686,
        2,
        11690,
        1,
        11696,
        4,
        11700,
        1,
        11707,
        7,
        11710,
        1,
        11717,
        9,
        11727,
        11,
        11730,
        2,
        11737,
        15,
        11740,
        1,
        11747,
        5,
        11757,
        8,
        11760,
        1,
        11767,
        3,
        11777,
        4,
        11780,
        1,
        11787,
        2,
        11797,
        7,
        11808,
        3,
        11818,
        3,
        11828,
        2,
        11838,
        3,
        11848,
        1,
        11868,
        1,
        11880,
        1,
        11898,
        1,
        11900,
        2,
        11909,
        1,
        11920,
        1,
        11939,
        1,
        11940,
        2,
        11949,
        2,
        11959,
        1,
        11969,
        1,
        11979,
        1,
        12020,
        1,
        12040,
        1,
        12060,
        1,
        12070,
        3,
        12080,
        1,
        12090,
        1,
        12100,
        6,
        12101,
        1,
        12110,
        5,
        12120,
        4,
        12130,
        7,
        12140,
        19,
        12141,
        1,
        12150,
        19,
        12160,
        13,
        12170,
        22,
        12171,
        1,
        12180,
        15,
        12190,
        14,
        12191,
        3,
        12200,
        20,
        12202,
        3,
        12210,
        22,
        12212,
        6,
        12220,
        31,
        12222,
        5,
        12230,
        38,
        12232,
        2,
        12240,
        25,
        12242,
        14,
        12250,
        36,
        12252,
        13,
        12260,
        42,
        12262,
        15,
        12270,
        33,
        12272,
        17,
        12280,
        29,
        12282,
        19,
        12290,
        14,
        12292,
        21,
        12300,
        15,
        12303,
        21,
        12310,
        11,
        12313,
        18,
        12320,
        13,
        12323,
        13,
        12330,
        3,
        12333,
        29,
        12340,
        8,
        12343,
        20,
        12350,
        4,
        12353,
        34,
        12360,
        3,
        12363,
        34,
        12370,
        2,
        12373,
        38,
        12380,
        3,
        12383,
        25,
        12393,
        28,
        12400,
        1,
        12404,
        20,
        12410,
        4,
        12414,
        15,
        12420,
        3,
        12424,
        12,
        12430,
        3,
        12434,
        10,
        12440,
        2,
        12444,
        6,
        12454,
        10,
        12464,
        5,
        12470,
        2,
        12474,
        6,
        12480,
        1,
        12484,
        1,
        12490,
        1,
        12494,
        7,
        12505,
        2,
        12515,
        2,
        12525,
        2,
        12530,
        1,
        12535,
        4,
        12545,
        4,
        12555,
        1,
        12565,
        2,
        12585,
        2,
        12606,
        3,
        12636,
        1,
        12656,
        1,
        12686,
        2,
        12696,
        1
      ],
      "errors": {
        "connect": 0,
        "read": 0,
        "write": 0,
        "status": 0,
        "timeout": 0
      }
    }
  }
}