{
  "version": "wrk:2",
  "settings": {
    "wrk_binary": "wrk",
    "wrk_concurrency": 1,
    "wrk_connections": 5,
    "warmup_seconds": 240,
    "benchmark_seconds": 480,
    "wrk_script_location": "./final_report.lua",
    "wrk_close_connection": false,
    "before_worker_cmd": "rvm use 2.6.2 && bundle",
    "ruby_change_cmd": "bash -l -c \"rvm use 2.6.2 && bundle && ruby /home/ubuntu/rsb/wrk_subprocess.rb /tmp/benchlib_17686.json\"",
    "json_filename": "/tmp/benchlib_17686.json",
    "wrk_subprocess": "/home/ubuntu/rsb/wrk_subprocess.rb",
    "rack_env": "production",
    "bundle_gemfile": "Gemfile.2.6.2",
    "bundler_version": "1.17.3",
    "extra_env": {
      "RSB_EXTRA_GEMFILES": "Gemfile.puma",
      "RSB_RUN_INDEX": 6
    },
    "port": 4321,
    "timestamp": 1557497422,
    "url": "http://127.0.0.1:4321/static",
    "out_file": "/home/ubuntu/rsb/data/rsb_rails_1557497422.json",
    "verbose": 1,
    "server_cmd": "bundle exec puma -p 4321 -t 1:1  --tag puma_rsb_rails_17686",
    "server_pre_cmd": "bundle && bundle exec rake db:migrate",
    "server_kill_command": null,
    "server_kill_matcher": "puma_rsb_rails_17686",
    "suppress_server_output": false
  },
  "environment": {
    "RUBY_VERSION": "2.6.2",
    "RUBY_DESCRIPTION": "ruby 2.6.2p47 (2019-03-13 revision 67232) [x86_64-linux]",
    "rvm current": "ruby-2.6.2",
    "repo git sha": "2467a3a8189a2a10d034d3bbc7235b78f9dcb8b6",
    "repo status": "On branch master\nYour branch is up-to-date with 'origin/master'.\nChanges not staged for commit:\n  (use \"git add <file>...\" to update what will be committed)\n  (use \"git checkout -- <file>...\" to discard changes in working directory)\n\n\tmodified:   runners/batching/config_jit.json\n\nUntracked files:\n  (use \"git add <file>...\" to include in what will be committed)\n\n\tnohup.out\n\nno changes added to commit (use \"git add\" and/or \"git commit -a\")\n",
    "uname": "Linux ip-172-31-28-43 4.4.0-1049-aws #58-Ubuntu SMP Fri Jan 12 23:17:09 UTC 2018 x86_64 x86_64 x86_64 GNU/Linux\n",
    "dir": "/home/ubuntu/rsb/rails_test_app",
    "env-LD_PRELOAD": null,
    "env-GEM_HOME": "/home/ubuntu/.rvm/gems/ruby-2.6.2",
    "env-RSB_EXTRA_GEMFILES": "Gemfile.puma",
    "env-MY_RUBY_HOME": "/home/ubuntu/.rvm/rubies/ruby-2.6.2",
    "env-BUNDLE_GEMFILE": "Gemfile.2.6.2",
    "env-RSB_RUN_INDEX": "6",
    "env-rvm_ruby_string": "ruby-2.6.2",
    "env-GEM_PATH": "/home/ubuntu/.rvm/gems/ruby-2.6.2:/home/ubuntu/.rvm/gems/ruby-2.6.2@global",
    "env-RUBY_VERSION": "ruby-2.6.2",
    "env-BUNDLER_ORIG_BUNDLE_GEMFILE": "Gemfile.2.6.2",
    "env-BUNDLER_ORIG_GEM_HOME": "/home/ubuntu/.rvm/gems/ruby-2.6.2",
    "env-BUNDLER_ORIG_GEM_PATH": "/home/ubuntu/.rvm/gems/ruby-2.6.2:/home/ubuntu/.rvm/gems/ruby-2.6.2@global",
    "env-BUNDLER_ORIG_RUBYLIB": "BUNDLER_ENVIRONMENT_PRESERVER_INTENTIONALLY_NIL",
    "env-BUNDLER_ORIG_RUBYOPT": "BUNDLER_ENVIRONMENT_PRESERVER_INTENTIONALLY_NIL",
    "wrk_path": "/usr/bin/wrk\n"
  },
  "requests": {
    "warmup": {
      "latencies": [
        716,
        1,
        717,
        5,
        718,
        4,
        719,
        1,
        720,
        2,
        721,
        2,
        723,
        6,
        724,
        12,
        725,
        23,
        726,
        96,
        727,
        294,
        728,
        879,
        729,
        2122,
        730,
        3975,
        731,
        6169,
        732,
        8101,
        733,
        8937,
        734,
        7906,
        735,
        6128,
        736,
        4419,
        737,
        3105,
        738,
        2052,
        739,
        1368,
        740,
        995,
        741,
        723,
        742,
        527,
        743,
        509,
        744,
        938,
        745,
        2455,
        746,
        5627,
        747,
        10770,
        748,
        17653,
        749,
        23688,
        750,
        26465,
        751,
        25483,
        752,
        21507,
        753,
        16937,
        754,
        12288,
        755,
        9218,
        756,
        6794,
        757,
        5005,
        758,
        3530,
        759,
        2571,
        760,
        1829,
        761,
        1419,
        762,
        1103,
        763,
        878,
        764,
        827,
        765,
        897,
        766,
        1060,
        767,
        1414,
        768,
        1744,
        769,
        2380,
        770,
        3223,
        771,
        3810,
        772,
        4439,
        773,
        4644,
        774,
        4239,
        775,
        3485,
        776,
        2740,
        777,
        2196,
        778,
        1674,
        779,
        1396,
        780,
        1072,
        781,
        834,
        782,
        597,
        783,
        509,
        784,
        321,
        785,
        229,
        786,
        201,
        787,
        124,
        788,
        93,
        789,
        83,
        790,
        52,
        791,
        39,
        792,
        44,
        793,
        39,
        794,
        30,
        795,
        23,
        796,
        18,
        797,
        23,
        798,
        23,
        799,
        21,
        800,
        15,
        801,
        15,
        802,
        15,
        803,
        17,
        804,
        9,
        805,
        6,
        806,
        7,
        807,
        12,
        808,
        8,
        809,
        5,
        810,
        11,
        811,
        7,
        812,
        5,
        813,
        9,
        814,
        5,
        816,
        9,
        817,
        4,
        818,
        6,
        819,
        7,
        820,
        6,
        822,
        6,
        823,
        6,
        824,
        7,
        825,
        7,
        826,
        9,
        827,
        10,
        828,
        16,
        829,
        12,
        830,
        11,
        831,
        11,
        832,
        9,
        833,
        3,
        834,
        5,
        835,
        2,
        836,
        4,
        837,
        2,
        839,
        5,
        840,
        2,
        841,
        1,
        842,
        2,
        843,
        3,
        844,
        3,
        845,
        2,
        846,
        2,
        847,
        2,
        848,
        2,
        850,
        2,
        851,
        2,
        852,
        4,
        853,
        3,
        854,
        2,
        855,
        1,
        856,
        2,
        858,
        1,
        859,
        2,
        860,
        2,
        863,
        1,
        865,
        1,
        867,
        2,
        871,
        1,
        873,
        1,
        880,
        2,
        898,
        1,
        908,
        1,
        927,
        1,
        937,
        1,
        942,
        1,
        943,
        1,
        950,
        1,
        955,
        3,
        957,
        1,
        958,
        1,
        959,
        2,
        960,
        3,
        961,
        1,
        962,
        5,
        963,
        6,
        964,
        4,
        965,
        5,
        966,
        14,
        967,
        13,
        968,
        9,
        969,
        23,
        970,
        26,
        971,
        16,
        972,
        32,
        973,
        23,
        974,
        20,
        975,
        32,
        976,
        34,
        977,
        33,
        978,
        36,
        979,
        57,
        980,
        56,
        981,
        58,
        982,
        61,
        983,
        59,
        984,
        52,
        985,
        49,
        986,
        53,
        987,
        48,
        988,
        65,
        989,
        57,
        990,
        55,
        991,
        45,
        992,
        75,
        993,
        54,
        994,
        57,
        995,
        48,
        996,
        57,
        997,
        52,
        998,
        53,
        999,
        65,
        1000,
        40,
        1001,
        44,
        1002,
        45,
        1003,
        39,
        1004,
        27,
        1005,
        44,
        1006,
        42,
        1007,
        41,
        1008,
        32,
        1009,
        37,
        1010,
        31,
        1011,
        36,
        1012,
        45,
        1013,
        43,
        1014,
        39,
        1015,
        50,
        1016,
        52,
        1017,
        50,
        1018,
        59,
        1019,
        66,
        1020,
        76,
        1021,
        65,
        1022,
        51,
        1023,
        59,
        1024,
        54,
        1025,
        38,
        1026,
        36,
        1027,
        22,
        1028,
        20,
        1029,
        15,
        1030,
        28,
        1031,
        19,
        1032,
        21,
        1033,
        19,
        1034,
        9,
        1035,
        20,
        1036,
        17,
        1037,
        19,
        1038,
        23,
        1039,
        21,
        1040,
        16,
        1041,
        14,
        1042,
        13,
        1043,
        12,
        1044,
        16,
        1045,
        19,
        1046,
        17,
        1047,
        12,
        1048,
        10,
        1049,
        5,
        1050,
        8,
        1051,
        2,
        1052,
        5,
        1053,
        2,
        1054,
        3,
        1055,
        3,
        1056,
        3,
        1057,
        2,
        1058,
        3,
        1059,
        3,
        1060,
        1,
        1061,
        3,
        1062,
        2,
        1064,
        1,
        1074,
        1,
        1083,
        1,
        1085,
        1,
        1095,
        1,
        1097,
        1,
        1101,
        1,
        1105,
        1,
        1106,
        1,
        1110,
        1,
        1111,
        1,
        1114,
        1,
        1116,
        1,
        1119,
        1,
        1121,
        1,
        1123,
        1,
        1134,
        2,
        1168,
        1,
        1180,
        1,
        1181,
        1,
        1224,
        1,
        1244,
        1,
        1245,
        1,
        1268,
        1,
        1300,
        1,
        1333,
        1,
        1361,
        1,
        1374,
        1,
        1380,
        1,
        1386,
        1,
        1416,
        2,
        1432,
        1,
        1438,
        2,
        1446,
        1,
        1447,
        1,
        1448,
        1,
        1449,
        1,
        1462,
        1,
        1468,
        1,
        1470,
        1,
        1473,
        2,
        1477,
        1,
        1480,
        1,
        1485,
        2,
        1487,
        1,
        1489,
        1,
        1490,
        1,
        1495,
        2,
        1496,
        2,
        1497,
        2,
        1498,
        1,
        1499,
        1,
        1500,
        1,
        1501,
        1,
        1507,
        1,
        1508,
        3,
        1509,
        1,
        1517,
        1,
        1519,
        2,
        1521,
        1,
        1523,
        1,
        1524,
        1,
        1528,
        1,
        1529,
        2,
        1530,
        2,
        1531,
        3,
        1534,
        1,
        1535,
        2,
        1536,
        3,
        1537,
        2,
        1539,
        2,
        1540,
        2,
        1541,
        2,
        1542,
        1,
        1546,
        1,
        1549,
        1,
        1550,
        2,
        1551,
        2,
        1552,
        1,
        1555,
        1,
        1558,
        2,
        1559,
        1,
        1560,
        2,
        1561,
        1,
        1563,
        2,
        1564,
        2,
        1565,
        2,
        1567,
        1,
        1571,
        1,
        1572,
        1,
        1575,
        1,
        1576,
        4,
        1577,
        1,
        1578,
        1,
        1579,
        2,
        1584,
        2,
        1587,
        3,
        1590,
        1,
        1591,
        1,
        1593,
        2,
        1596,
        3,
        1597,
        1,
        1598,
        1,
        1599,
        2,
        1600,
        2,
        1601,
        1,
        1602,
        1,
        1603,
        2,
        1604,
        1,
        1605,
        2,
        1606,
        3,
        1607,
        1,
        1608,
        1,
        1609,
        2,
        1610,
        2,
        1612,
        1,
        1616,
        1,
        1617,
        1,
        1622,
        2,
        1624,
        1,
        1625,
        1,
        1626,
        2,
        1627,
        1,
        1629,
        2,
        1630,
        1,
        1631,
        1,
        1633,
        3,
        1634,
        1,
        1635,
        2,
        1636,
        1,
        1638,
        2,
        1639,
        1,
        1640,
        2,
        1641,
        1,
        1642,
        1,
        1644,
        1,
        1645,
        2,
        1646,
        2,
        1647,
        2,
        1648,
        2,
        1649,
        2,
        1650,
        1,
        1651,
        1,
        1652,
        1,
        1653,
        2,
        1655,
        1,
        1657,
        1,
        1659,
        1,
        1660,
        1,
        1661,
        1,
        1663,
        3,
        1665,
        1,
        1666,
        2,
        1667,
        1,
        1668,
        2,
        1669,
        2,
        1670,
        1,
        1671,
        3,
        1672,
        2,
        1673,
        2,
        1674,
        1,
        1675,
        4,
        1677,
        1,
        1680,
        1,
        1681,
        1,
        1683,
        2,
        1684,
        1,
        1685,
        2,
        1686,
        1,
        1687,
        2,
        1689,
        3,
        1690,
        1,
        1691,
        1,
        1692,
        1,
        1694,
        1,
        1696,
        1,
        1697,
        1,
        1698,
        2,
        1699,
        2,
        1700,
        1,
        1701,
        1,
        1702,
        1,
        1703,
        1,
        1704,
        2,
        1705,
        2,
        1707,
        3,
        1708,
        1,
        1709,
        1,
        1710,
        1,
        1712,
        1,
        1713,
        2,
        1714,
        1,
        1716,
        1,
        1717,
        2,
        1718,
        2,
        1721,
        2,
        1722,
        1,
        1723,
        2,
        1725,
        2,
        1726,
        1,
        1727,
        1,
        1728,
        1,
        1729,
        3,
        1730,
        2,
        1731,
        1,
        1732,
        1,
        1734,
        2,
        1735,
        1,
        1736,
        1,
        1737,
        1,
        1738,
        2,
        1739,
        3,
        1740,
        2,
        1742,
        2,
        1744,
        3,
        1745,
        2,
        1746,
        2,
        1747,
        3,
        1748,
        1,
        1749,
        1,
        1750,
        1,
        1751,
        1,
        1752,
        1,
        1753,
        1,
        1754,
        1,
        1755,
        1,
        1756,
        1,
        1758,
        1,
        1760,
        1,
        1763,
        1,
        1766,
        1,
        1770,
        1,
        1771,
        1,
        1772,
        1,
        1773,
        1,
        1774,
        4,
        1777,
        1,
        1778,
        1,
        1779,
        1,
        1781,
        2,
        1789,
        1,
        1790,
        1,
        1791,
        3,
        1800,
        1,
        1802,
        1,
        1803,
        2,
        1806,
        1,
        1810,
        1,
        1820,
        1,
        1822,
        1,
        1824,
        1,
        1839,
        1,
        1840,
        1,
        1850,
        1,
        1857,
        1,
        1859,
        1,
        1867,
        1,
        1883,
        1,
        1893,
        1,
        1907,
        1,
        1933,
        1,
        2169,
        1,
        2290,
        1,
        2340,
        1,
        2348,
        1,
        2374,
        1,
        2414,
        1,
        2444,
        1,
        2448,
        1,
        2457,
        1,
        2479,
        1,
        2480,
        1,
        2502,
        1,
        2508,
        1,
        2517,
        1,
        2525,
        1,
        2531,
        2,
        2538,
        1,
        2548,
        1,
        2549,
        1,
        2557,
        1,
        2558,
        1,
        2563,
        1,
        2564,
        2,
        2565,
        2,
        2569,
        2,
        2570,
        1,
        2571,
        2,
        2573,
        1,
        2574,
        2,
        2581,
        1,
        2582,
        2,
        2584,
        2,
        2585,
        4,
        2587,
        1,
        2588,
        1,
        2589,
        1,
        2590,
        1,
        2591,
        1,
        2593,
        2,
        2594,
        1,
        2596,
        1,
        2599,
        2,
        2600,
        2,
        2601,
        3,
        2602,
        2,
        2604,
        2,
        2605,
        2,
        2606,
        5,
        2607,
        1,
        2608,
        3,
        2609,
        3,
        2610,
        5,
        2611,
        3,
        2612,
        6,
        2613,
        2,
        2614,
        2,
        2615,
        6,
        2616,
        3,
        2617,
        3,
        2618,
        6,
        2619,
        6,
        2620,
        5,
        2621,
        7,
        2622,
        5,
        2623,
        5,
        2624,
        3,
        2625,
        2,
        2626,
        7,
        2627,
        6,
        2628,
        1,
        2629,
        5,
        2630,
        6,
        2631,
        3,
        2632,
        7,
        2633,
        5,
        2634,
        4,
        2635,
        3,
        2636,
        8,
        2637,
        3,
        2638,
        4,
        2639,
        11,
        2640,
        9,
        2641,
        4,
        2642,
        2,
        2643,
        4,
        2644,
        8,
        2645,
        1,
        2646,
        4,
        2647,
        7,
        2648,
        4,
        2649,
        6,
        2650,
        5,
        2651,
        4,
        2652,
        10,
        2653,
        9,
        2654,
        7,
        2655,
        6,
        2656,
        1,
        2657,
        8,
        2658,
        5,
        2659,
        5,
        2660,
        7,
        2661,
        3,
        2662,
        5,
        2663,
        2,
        2664,
        8,
        2665,
        2,
        2666,
        4,
        2667,
        2,
        2668,
        4,
        2669,
        5,
        2670,
        5,
        2671,
        10,
        2672,
        3,
        2673,
        5,
        2674,
        8,
        2675,
        4,
        2676,
        3,
        2677,
        5,
        2678,
        6,
        2679,
        3,
        2680,
        3,
        2681,
        5,
        2682,
        5,
        2683,
        2,
        2684,
        7,
        2685,
        6,
        2686,
        9,
        2687,
        7,
        2688,
        5,
        2689,
        7,
        2690,
        13,
        2691,
        4,
        2692,
        6,
        2693,
        8,
        2694,
        6,
        2695,
        8,
        2696,
        1,
        2697,
        2,
        2698,
        5,
        2699,
        9,
        2700,
        8,
        2701,
        3,
        2702,
        8,
        2703,
        5,
        2704,
        3,
        2705,
        4,
        2706,
        5,
        2707,
        5,
        2708,
        5,
        2709,
        8,
        2710,
        11,
        2711,
        6,
        2712,
        3,
        2713,
        9,
        2714,
        4,
        2715,
        6,
        2716,
        5,
        2717,
        3,
        2718,
        10,
        2719,
        9,
        2720,
        5,
        2721,
        7,
        2722,
        9,
        2723,
        6,
        2724,
        6,
        2725,
        5,
        2726,
        4,
        2727,
        5,
        2728,
        5,
        2729,
        3,
        2730,
        6,
        2731,
        6,
        2732,
        5,
        2733,
        6,
        2734,
        3,
        2735,
        2,
        2736,
        3,
        2737,
        6,
        2738,
        4,
        2739,
        2,
        2740,
        7,
        2741,
        5,
        2742,
        4,
        2743,
        8,
        2744,
        8,
        2745,
        13,
        2746,
        8,
        2747,
        8,
        2748,
        5,
        2749,
        4,
        2750,
        6,
        2751,
        3,
        2752,
        6,
        2753,
        3,
        2754,
        6,
        2755,
        4,
        2756,
        5,
        2757,
        4,
        2758,
        3,
        2759,
        4,
        2760,
        8,
        2761,
        4,
        2762,
        7,
        2763,
        7,
        2764,
        9,
        2765,
        4,
        2766,
        2,
        2767,
        4,
        2768,
        7,
        2769,
        7,
        2770,
        11,
        2771,
        3,
        2772,
        8,
        2773,
        4,
        2774,
        3,
        2775,
        5,
        2776,
        4,
        2777,
        7,
        2778,
        8,
        2779,
        5,
        2780,
        7,
        2781,
        3,
        2782,
        10,
        2783,
        7,
        2784,
        7,
        2785,
        5,
        2786,
        7,
        2787,
        4,
        2788,
        5,
        2789,
        6,
        2790,
        3,
        2791,
        6,
        2792,
        7,
        2793,
        2,
        2794,
        3,
        2795,
        9,
        2796,
        6,
        2797,
        5,
        2798,
        2,
        2799,
        5,
        2800,
        5,
        2801,
        4,
        2802,
        4,
        2803,
        6,
        2804,
        5,
        2805,
        4,
        2806,
        6,
        2807,
        9,
        2808,
        5,
        2809,
        6,
        2810,
        5,
        2811,
        3,
        2812,
        6,
        2813,
        10,
        2814,
        10,
        2815,
        11,
        2816,
        7,
        2817,
        6,
        2818,
        5,
        2819,
        10,
        2820,
        4,
        2821,
        4,
        2822,
        5,
        2823,
        5,
        2824,
        5,
        2825,
        6,
        2826,
        5,
        2827,
        8,
        2828,
        8,
        2829,
        4,
        2830,
        8,
        2831,
        6,
        2832,
        2,
        2833,
        2,
        2834,
        3,
        2835,
        4,
        2836,
        6,
        2837,
        5,
        2838,
        4,
        2839,
        7,
        2840,
        9,
        2841,
        5,
        2842,
        6,
        2843,
        8,
        2844,
        9,
        2845,
        6,
        2846,
        3,
        2847,
        6,
        2848,
        5,
        2849,
        2,
        2850,
        6,
        2851,
        5,
        2852,
        6,
        2853,
        2,
        2854,
        4,
        2855,
        4,
        2856,
        4,
        2857,
        2,
        2858,
        10,
        2859,
        9,
        2860,
        8,
        2861,
        4,
        2862,
        12,
        2863,
        3,
        2864,
        5,
        2865,
        7,
        2866,
        3,
        2867,
        10,
        2868,
        5,
        2869,
        6,
        2870,
        6,
        2871,
        3,
        2872,
        8,
        2873,
        8,
        2874,
        7,
        2875,
        3,
        2876,
        7,
        2877,
        4,
        2878,
        4,
        2879,
        6,
        2880,
        5,
        2881,
        4,
        2882,
        4,
        2883,
        10,
        2884,
        3,
        2885,
        5,
        2886,
        5,
        2887,
        11,
        2888,
        5,
        2889,
        1,
        2890,
        4,
        2891,
        4,
        2892,
        4,
        2893,
        5,
        2894,
        3,
        2895,
        6,
        2896,
        2,
        2897,
        5,
        2898,
        13,
        2899,
        6,
        2900,
        7,
        2901,
        6,
        2902,
        5,
        2903,
        4,
        2904,
        7,
        2905,
        5,
        2906,
        6,
        2907,
        8,
        2908,
        9,
        2909,
        8,
        2910,
        10,
        2911,
        7,
        2912,
        7,
        2913,
        5,
        2914,
        7,
        2915,
        9,
        2916,
        11,
        2917,
        9,
        2918,
        7,
        2919,
        10,
        2920,
        4,
        2921,
        6,
        2922,
        4,
        2923,
        9,
        2924,
        9,
        2925,
        6,
        2926,
        5,
        2927,
        11,
        2928,
        7,
        2929,
        4,
        2930,
        3,
        2931,
        6,
        2932,
        5,
        2933,
        3,
        2934,
        4,
        2935,
        6,
        2936,
        6,
        2937,
        8,
        2938,
        9,
        2939,
        5,
        2940,
        8,
        2941,
        5,
        2942,
        11,
        2943,
        5,
        2944,
        9,
        2945,
        7,
        2946,
        6,
        2947,
        7,
        2948,
        6,
        2949,
        7,
        2950,
        5,
        2951,
        3,
        2952,
        9,
        2953,
        8,
        2954,
        6,
        2955,
        3,
        2956,
        6,
        2957,
        8,
        2958,
        9,
        2959,
        8,
        2960,
        8,
        2961,
        3,
        2962,
        6,
        2963,
        7,
        2964,
        5,
        2965,
        6,
        2966,
        6,
        2967,
        9,
        2968,
        10,
        2969,
        5,
        2970,
        9,
        2971,
        9,
        2972,
        4,
        2973,
        7,
        2974,
        6,
        2975,
        5,
        2976,
        3,
        2977,
        4,
        2978,
        5,
        2979,
        5,
        2980,
        8,
        2981,
        9,
        2982,
        8,
        2984,
        10,
        2985,
        10,
        2986,
        8,
        2987,
        9,
        2988,
        5,
        2989,
        4,
        2990,
        7,
        2991,
        3,
        2992,
        5,
        2993,
        8,
        2994,
        5,
        2995,
        9,
        2996,
        3,
        2997,
        6,
        2998,
        3,
        2999,
        2,
        3000,
        6,
        3001,
        6,
        3002,
        1,
        3003,
        9,
        3004,
        4,
        3005,
        6,
        3006,
        3,
        3007,
        5,
        3008,
        13,
        3009,
        7,
        3010,
        8,
        3011,
        7,
        3012,
        7,
        3013,
        7,
        3014,
        4,
        3015,
        5,
        3016,
        6,
        3017,
        10,
        3018,
        6,
        3019,
        11,
        3020,
        6,
        3021,
        3,
        3022,
        7,
        3023,
        7,
        3024,
        4,
        3025,
        6,
        3026,
        7,
        3027,
        2,
        3028,
        8,
        3029,
        5,
        3030,
        5,
        3031,
        5,
        3032,
        7,
        3033,
        11,
        3034,
        4,
        3035,
        8,
        3036,
        5,
        3037,
        6,
        3038,
        4,
        3039,
        5,
        3040,
        7,
        3041,
        5,
        3042,
        11,
        3043,
        5,
        3044,
        6,
        3045,
        11,
        3046,
        8,
        3047,
        8,
        3048,
        3,
        3049,
        7,
        3050,
        11,
        3051,
        9,
        3052,
        5,
        3053,
        3,
        3054,
        4,
        3055,
        10,
        3056,
        7,
        3057,
        5,
        3058,
        8,
        3059,
        2,
        3060,
        2,
        3061,
        8,
        3062,
        7,
        3063,
        5,
        3064,
        3,
        3065,
        4,
        3066,
        4,
        3067,
        5,
        3068,
        4,
        3069,
        7,
        3070,
        8,
        3071,
        3,
        3072,
        3,
        3073,
        4,
        3074,
        8,
        3075,
        3,
        3076,
        8,
        3077,
        5,
        3078,
        9,
        3079,
        7,
        3080,
        5,
        3081,
        8,
        3082,
        6,
        3083,
        13,
        3084,
        3,
        3085,
        4,
        3086,
        8,
        3087,
        6,
        3088,
        8,
        3089,
        8,
        3090,
        2,
        3091,
        4,
        3092,
        8,
        3093,
        4,
        3094,
        10,
        3095,
        2,
        3096,
        4,
        3097,
        5,
        3098,
        6,
        3099,
        6,
        3100,
        1,
        3101,
        4,
        3102,
        7,
        3103,
        11,
        3104,
        5,
        3105,
        5,
        3106,
        8,
        3107,
        8,
        3108,
        6,
        3109,
        5,
        3110,
        6,
        3111,
        3,
        3112,
        10,
        3113,
        8,
        3114,
        8,
        3115,
        7,
        3116,
        8,
        3117,
        7,
        3118,
        7,
        3119,
        4,
        3120,
        4,
        3121,
        3,
        3122,
        9,
        3123,
        11,
        3124,
        5,
        3125,
        7,
        3126,
        12,
        3127,
        9,
        3128,
        7,
        3129,
        3,
        3130,
        4,
        3131,
        4,
        3132,
        6,
        3133,
        8,
        3134,
        4,
        3135,
        4,
        3136,
        4,
        3137,
        8,
        3138,
        4,
        3139,
        2,
        3140,
        4,
        3141,
        8,
        3142,
        5,
        3143,
        10,
        3144,
        5,
        3145,
        5,
        3146,
        9,
        3147,
        4,
        3148,
        8,
        3149,
        2,
        3150,
        1,
        3151,
        6,
        3152,
        9,
        3153,
        3,
        3154,
        1,
        3155,
        4,
        3156,
        3,
        3157,
        3,
        3158,
        6,
        3159,
        4,
        3160,
        6,
        3161,
        4,
        3162,
        9,
        3163,
        10,
        3164,
        6,
        3165,
        2,
        3166,
        5,
        3167,
        4,
        3168,
        1,
        3169,
        7,
        3170,
        5,
        3171,
        6,
        3172,
        1,
        3173,
        4,
        3174,
        3,
        3175,
        3,
        3176,
        3,
        3177,
        3,
        3178,
        5,
        3179,
        3,
        3180,
        1,
        3181,
        4,
        3183,
        4,
        3184,
        2,
        3185,
        3,
        3186,
        7,
        3187,
        6,
        3188,
        1,
        3189,
        2,
        3190,
        2,
        3191,
        3,
        3193,
        1,
        3194,
        2,
        3195,
        3,
        3196,
        3,
        3197,
        1,
        3199,
        2,
        3200,
        1,
        3201,
        3,
        3202,
        1,
        3203,
        2,
        3204,
        1,
        3205,
        1,
        3206,
        1,
        3207,
        1,
        3208,
        4,
        3209,
        2,
        3210,
        2,
        3211,
        1,
        3212,
        2,
        3213,
        3,
        3214,
        1,
        3216,
        2,
        3218,
        1,
        3221,
        3,
        3223,
        4,
        3224,
        1,
        3226,
        1,
        3227,
        2,
        3228,
        1,
        3229,
        1,
        3230,
        1,
        3231,
        1,
        3232,
        1,
        3233,
        1,
        3235,
        1,
        3237,
        1,
        3242,
        1,
        3244,
        1,
        3245,
        2,
        3247,
        2,
        3251,
        1,
        3252,
        1,
        3253,
        1,
        3256,
        2,
        3260,
        2,
        3261,
        1,
        3263,
        2,
        3264,
        1,
        3265,
        1,
        3266,
        1,
        3267,
        1,
        3268,
        1,
        3269,
        1,
        3271,
        1,
        3272,
        1,
        3277,
        2,
        3278,
        1,
        3279,
        1,
        3284,
        1,
        3290,
        2,
        3291,
        1,
        3292,
        1,
        3293,
        2,
        3294,
        1,
        3300,
        2,
        3301,
        1,
        3302,
        1,
        3303,
        1,
        3304,
        3,
        3307,
        1,
        3308,
        2,
        3310,
        1,
        3312,
        2,
        3314,
        1,
        3315,
        2,
        3319,
        1,
        3320,
        1,
        3321,
        1,
        3322,
        2,
        3323,
        3,
        3324,
        1,
        3326,
        1,
        3328,
        1,
        3329,
        1,
        3330,
        1,
        3334,
        1,
        3336,
        1,
        3338,
        2,
        3340,
        3,
        3341,
        4,
        3342,
        2,
        3343,
        3,
        3344,
        3,
        3345,
        2,
        3347,
        1,
        3348,
        3,
        3349,
        1,
        3350,
        2,
        3351,
        2,
        3353,
        1,
        3354,
        1,
        3356,
        1,
        3357,
        2,
        3358,
        2,
        3360,
        1,
        3361,
        1,
        3363,
        1,
        3364,
        1,
        3365,
        1,
        3366,
        2,
        3367,
        3,
        3368,
        2,
        3369,
        1,
        3370,
        2,
        3371,
        3,
        3374,
        1,
        3375,
        2,
        3378,
        1,
        3379,
        1,
        3380,
        1,
        3403,
        1,
        3405,
        1,
        3415,
        1,
        3428,
        1,
        3434,
        1,
        3449,
        1,
        3461,
        1,
        3495,
        1,
        3496,
        1,
        3499,
        1,
        3509,
        1,
        3535,
        1,
        3556,
        1,
        3583,
        1,
        3584,
        1,
        3612,
        1,
        3648,
        1,
        3834,
        1,
        4088,
        1,
        4218,
        1,
        4309,
        1,
        4323,
        1,
        5195,
        1,
        6207,
        1,
        6426,
        1,
        6490,
        1,
        6511,
        1,
        6516,
        1,
        6534,
        1,
        6574,
        1,
        6579,
        1,
        6647,
        1,
        6661,
        1,
        8002,
        1,
        8132,
        1,
        8223,
        1,
        9109,
        1
      ],
      "req_per_sec": [
        808,
        1,
        810,
        1,
        820,
        1,
        830,
        2,
        838,
        2,
        868,
        1,
        970,
        1,
        980,
        1,
        1010,
        1,
        1030,
        1,
        1040,
        1,
        1111,
        1,
        1121,
        1,
        1130,
        1,
        1161,
        1,
        1181,
        1,
        1240,
        1,
        1250,
        5,
        1260,
        238,
        1262,
        138,
        1270,
        227,
        1272,
        271,
        1280,
        110,
        1282,
        143,
        1287,
        1,
        1290,
        368,
        1292,
        156,
        1300,
        167,
        1303,
        232,
        1310,
        96,
        1313,
        162,
        1320,
        31,
        1323,
        34,
        1333,
        2
      ],
      "errors": {
        "connect": 0,
        "read": 0,
        "write": 0,
        "status": 0,
        "timeout": 0
      }
    },
    "benchmark": {
      "latencies": [
        714,
        1,
        717,
        3,
        718,
        8,
        719,
        2,
        720,
        5,
        721,
        9,
        722,
        16,
        723,
        8,
        724,
        5,
        725,
        31,
        726,
        124,
        727,
        413,
        728,
        1302,
        729,
        2755,
        730,
        4962,
        731,
        7427,
        732,
        9452,
        733,
        10295,
        734,
        9073,
        735,
        7034,
        736,
        4770,
        737,
        3230,
        738,
        2274,
        739,
        1479,
        740,
        1059,
        741,
        700,
        742,
        575,
        743,
        602,
        744,
        1149,
        745,
        2957,
        746,
        6662,
        747,
        12909,
        748,
        21265,
        749,
        28745,
        750,
        33572,
        751,
        34367,
        752,
        33391,
        753,
        33369,
        754,
        34708,
        755,
        35467,
        756,
        34131,
        757,
        30283,
        758,
        24258,
        759,
        18145,
        760,
        12909,
        761,
        9032,
        762,
        6446,
        763,
        4786,
        764,
        3429,
        765,
        2817,
        766,
        2733,
        767,
        2922,
        768,
        3411,
        769,
        4149,
        770,
        5052,
        771,
        6050,
        772,
        6989,
        773,
        7421,
        774,
        7407,
        775,
        7318,
        776,
        7112,
        777,
        6969,
        778,
        6600,
        779,
        5886,
        780,
        4870,
        781,
        3877,
        782,
        3104,
        783,
        2225,
        784,
        1737,
        785,
        1430,
        786,
        1065,
        787,
        805,
        788,
        605,
        789,
        495,
        790,
        354,
        791,
        296,
        792,
        209,
        793,
        184,
        794,
        150,
        795,
        107,
        796,
        79,
        797,
        60,
        798,
        58,
        799,
        51,
        800,
        50,
        801,
        44,
        802,
        48,
        803,
        45,
        804,
        42,
        805,
        25,
        806,
        18,
        807,
        39,
        808,
        22,
        809,
        26,
        810,
        24,
        811,
        19,
        812,
        13,
        813,
        16,
        814,
        18,
        815,
        12,
        816,
        15,
        817,
        10,
        818,
        10,
        819,
        11,
        820,
        14,
        821,
        16,
        822,
        11,
        823,
        12,
        824,
        15,
        825,
        8,
        826,
        13,
        827,
        12,
        828,
        21,
        829,
        15,
        830,
        19,
        831,
        12,
        832,
        24,
        833,
        14,
        834,
        17,
        835,
        19,
        836,
        15,
        837,
        13,
        838,
        11,
        839,
        8,
        840,
        11,
        841,
        9,
        842,
        10,
        844,
        7,
        846,
        3,
        847,
        4,
        848,
        6,
        849,
        4,
        850,
        2,
        851,
        7,
        852,
        6,
        853,
        6,
        854,
        8,
        855,
        6,
        856,
        2,
        857,
        3,
        858,
        6,
        859,
        3,
        860,
        3,
        861,
        1,
        862,
        2,
        863,
        2,
        864,
        3,
        865,
        2,
        866,
        2,
        867,
        4,
        871,
        1,
        873,
        1,
        874,
        1,
        876,
        2,
        877,
        1,
        878,
        1,
        879,
        2,
        880,
        1,
        888,
        1,
        909,
        1,
        912,
        1,
        913,
        1,
        917,
        1,
        936,
        1,
        939,
        1,
        944,
        1,
        945,
        1,
        947,
        2,
        949,
        1,
        950,
        1,
        951,
        1,
        952,
        1,
        956,
        2,
        957,
        1,
        958,
        2,
        959,
        3,
        960,
        3,
        961,
        3,
        962,
        2,
        963,
        5,
        964,
        6,
        965,
        12,
        966,
        10,
        967,
        10,
        968,
        20,
        969,
        24,
        970,
        23,
        971,
        33,
        972,
        33,
        973,
        42,
        974,
        39,
        975,
        55,
        976,
        45,
        977,
        61,
        978,
        75,
        979,
        83,
        980,
        71,
        981,
        56,
        982,
        77,
        983,
        93,
        984,
        81,
        985,
        93,
        986,
        81,
        987,
        81,
        988,
        95,
        989,
        109,
        990,
        89,
        991,
        104,
        992,
        104,
        993,
        103,
        994,
        110,
        995,
        100,
        996,
        124,
        997,
        119,
        998,
        128,
        999,
        100,
        1000,
        105,
        1001,
        93,
        1002,
        83,
        1003,
        89,
        1004,
        115,
        1005,
        95,
        1006,
        92,
        1007,
        93,
        1008,
        76,
        1009,
        88,
        1010,
        86,
        1011,
        101,
        1012,
        69,
        1013,
        70,
        1014,
        81,
        1015,
        76,
        1016,
        83,
        1017,
        102,
        1018,
        93,
        1019,
        108,
        1020,
        107,
        1021,
        100,
        1022,
        99,
        1023,
        96,
        1024,
        105,
        1025,
        89,
        1026,
        94,
        1027,
        88,
        1028,
        80,
        1029,
        78,
        1030,
        93,
        1031,
        88,
        1032,
        69,
        1033,
        67,
        1034,
        59,
        1035,
        59,
        1036,
        42,
        1037,
        40,
        1038,
        50,
        1039,
        38,
        1040,
        36,
        1041,
        40,
        1042,
        34,
        1043,
        37,
        1044,
        31,
        1045,
        35,
        1046,
        25,
        1047,
        21,
        1048,
        19,
        1049,
        22,
        1050,
        23,
        1051,
        21,
        1052,
        19,
        1053,
        15,
        1054,
        20,
        1055,
        12,
        1056,
        13,
        1057,
        7,
        1058,
        8,
        1059,
        7,
        1060,
        10,
        1061,
        6,
        1062,
        9,
        1063,
        7,
        1064,
        3,
        1065,
        2,
        1066,
        1,
        1067,
        2,
        1068,
        1,
        1069,
        1,
        1071,
        1,
        1072,
        1,
        1073,
        1,
        1074,
        3,
        1079,
        1,
        1083,
        2,
        1085,
        1,
        1091,
        1,
        1093,
        1,
        1094,
        1,
        1095,
        1,
        1097,
        1,
        1102,
        1,
        1104,
        1,
        1106,
        1,
        1109,
        2,
        1111,
        2,
        1112,
        1,
        1113,
        4,
        1114,
        1,
        1116,
        2,
        1119,
        1,
        1120,
        1,
        1121,
        1,
        1122,
        1,
        1123,
        1,
        1125,
        1,
        1131,
        1,
        1134,
        1,
        1135,
        1,
        1141,
        1,
        1142,
        1,
        1161,
        1,
        1163,
        1,
        1169,
        1,
        1176,
        1,
        1182,
        1,
        1217,
        1,
        1220,
        1,
        1238,
        1,
        1256,
        1,
        1267,
        1,
        1270,
        1,
        1276,
        1,
        1282,
        1,
        1288,
        1,
        1297,
        1,
        1298,
        1,
        1302,
        1,
        1315,
        1,
        1334,
        1,
        1338,
        1,
        1341,
        1,
        1349,
        1,
        1369,
        2,
        1374,
        1,
        1375,
        1,
        1376,
        1,
        1384,
        1,
        1386,
        2,
        1388,
        1,
        1389,
        1,
        1390,
        1,
        1392,
        1,
        1394,
        1,
        1395,
        1,
        1400,
        1,
        1403,
        1,
        1406,
        1,
        1408,
        1,
        1410,
        1,
        1412,
        1,
        1418,
        1,
        1419,
        1,
        1420,
        1,
        1421,
        2,
        1424,
        1,
        1430,
        1,
        1435,
        2,
        1437,
        1,
        1441,
        2,
        1443,
        1,
        1444,
        1,
        1449,
        1,
        1450,
        1,
        1451,
        1,
        1456,
        2,
        1459,
        1,
        1462,
        2,
        1463,
        1,
        1464,
        1,
        1471,
        1,
        1474,
        1,
        1475,
        3,
        1477,
        1,
        1480,
        1,
        1481,
        2,
        1482,
        1,
        1483,
        2,
        1484,
        2,
        1485,
        1,
        1486,
        2,
        1487,
        1,
        1488,
        1,
        1489,
        2,
        1491,
        2,
        1495,
        3,
        1496,
        2,
        1497,
        2,
        1498,
        1,
        1500,
        2,
        1501,
        2,
        1502,
        3,
        1505,
        2,
        1506,
        1,
        1508,
        2,
        1510,
        3,
        1512,
        2,
        1514,
        3,
        1516,
        1,
        1517,
        2,
        1518,
        3,
        1519,
        2,
        1520,
        2,
        1521,
        6,
        1522,
        3,
        1523,
        2,
        1524,
        3,
        1525,
        2,
        1527,
        3,
        1528,
        2,
        1529,
        1,
        1530,
        1,
        1531,
        1,
        1532,
        3,
        1533,
        3,
        1534,
        1,
        1536,
        2,
        1537,
        2,
        1538,
        3,
        1539,
        4,
        1540,
        4,
        1541,
        2,
        1542,
        3,
        1543,
        1,
        1545,
        1,
        1547,
        4,
        1548,
        3,
        1549,
        2,
        1550,
        1,
        1551,
        2,
        1552,
        3,
        1553,
        5,
        1554,
        4,
        1556,
        2,
        1557,
        2,
        1558,
        1,
        1559,
        1,
        1560,
        3,
        1561,
        1,
        1562,
        3,
        1563,
        1,
        1564,
        1,
        1565,
        2,
        1566,
        3,
        1567,
        2,
        1568,
        2,
        1569,
        1,
        1570,
        3,
        1571,
        3,
        1572,
        2,
        1573,
        1,
        1574,
        2,
        1575,
        1,
        1576,
        5,
        1577,
        2,
        1578,
        1,
        1580,
        2,
        1581,
        4,
        1582,
        1,
        1583,
        3,
        1584,
        4,
        1585,
        3,
        1586,
        4,
        1588,
        4,
        1589,
        6,
        1591,
        4,
        1592,
        1,
        1593,
        1,
        1594,
        4,
        1595,
        3,
        1596,
        2,
        1597,
        3,
        1598,
        3,
        1599,
        3,
        1600,
        2,
        1601,
        3,
        1602,
        3,
        1604,
        1,
        1605,
        2,
        1606,
        1,
        1607,
        3,
        1608,
        2,
        1609,
        3,
        1610,
        2,
        1611,
        2,
        1614,
        5,
        1615,
        2,
        1616,
        6,
        1617,
        5,
        1618,
        3,
        1619,
        6,
        1620,
        3,
        1621,
        1,
        1622,
        1,
        1625,
        5,
        1626,
        3,
        1627,
        5,
        1628,
        1,
        1629,
        1,
        1630,
        1,
        1631,
        3,
        1632,
        6,
        1633,
        6,
        1634,
        3,
        1635,
        4,
        1636,
        6,
        1637,
        3,
        1638,
        3,
        1639,
        1,
        1640,
        5,
        1641,
        3,
        1642,
        2,
        1643,
        3,
        1644,
        2,
        1645,
        1,
        1646,
        5,
        1647,
        3,
        1648,
        2,
        1649,
        5,
        1650,
        1,
        1652,
        4,
        1653,
        1,
        1654,
        2,
        1655,
        2,
        1656,
        5,
        1657,
        1,
        1658,
        3,
        1659,
        2,
        1660,
        1,
        1661,
        3,
        1662,
        1,
        1663,
        2,
        1664,
        2,
        1666,
        2,
        1667,
        5,
        1668,
        4,
        1669,
        3,
        1670,
        1,
        1671,
        2,
        1673,
        2,
        1674,
        1,
        1675,
        5,
        1676,
        4,
        1677,
        1,
        1678,
        1,
        1679,
        3,
        1680,
        3,
        1681,
        3,
        1682,
        2,
        1683,
        1,
        1684,
        2,
        1685,
        1,
        1686,
        2,
        1687,
        5,
        1688,
        2,
        1689,
        2,
        1690,
        1,
        1691,
        2,
        1692,
        2,
        1693,
        2,
        1694,
        1,
        1695,
        2,
        1696,
        5,
        1697,
        1,
        1698,
        1,
        1699,
        2,
        1700,
        2,
        1701,
        4,
        1702,
        1,
        1703,
        1,
        1704,
        3,
        1705,
        3,
        1706,
        2,
        1707,
        2,
        1708,
        2,
        1709,
        2,
        1710,
        1,
        1712,
        2,
        1713,
        2,
        1714,
        5,
        1715,
        1,
        1717,
        3,
        1719,
        3,
        1721,
        2,
        1722,
        2,
        1723,
        2,
        1724,
        1,
        1725,
        3,
        1726,
        7,
        1727,
        3,
        1728,
        2,
        1729,
        2,
        1730,
        4,
        1731,
        1,
        1732,
        3,
        1733,
        4,
        1734,
        5,
        1735,
        1,
        1736,
        2,
        1737,
        5,
        1738,
        3,
        1739,
        1,
        1740,
        3,
        1742,
        3,
        1743,
        2,
        1744,
        1,
        1745,
        3,
        1746,
        4,
        1748,
        3,
        1749,
        3,
        1750,
        1,
        1751,
        2,
        1752,
        2,
        1753,
        1,
        1754,
        3,
        1755,
        3,
        1756,
        3,
        1757,
        1,
        1758,
        3,
        1759,
        2,
        1760,
        1,
        1761,
        1,
        1762,
        1,
        1765,
        1,
        1767,
        1,
        1771,
        1,
        1772,
        4,
        1773,
        1,
        1774,
        4,
        1775,
        2,
        1776,
        1,
        1777,
        2,
        1778,
        1,
        1779,
        1,
        1782,
        2,
        1783,
        2,
        1785,
        1,
        1786,
        1,
        1787,
        1,
        1788,
        1,
        1789,
        1,
        1791,
        3,
        1793,
        2,
        1794,
        1,
        1795,
        1,
        1797,
        2,
        1799,
        2,
        1800,
        1,
        1801,
        1,
        1802,
        1,
        1803,
        1,
        1804,
        1,
        1805,
        2,
        1807,
        1,
        1809,
        1,
        1810,
        1,
        1812,
        2,
        1813,
        1,
        1814,
        1,
        1825,
        2,
        1827,
        1,
        1828,
        1,
        1829,
        1,
        1832,
        2,
        1833,
        1,
        1834,
        1,
        1839,
        2,
        1840,
        1,
        1842,
        2,
        1843,
        1,
        1860,
        1,
        1864,
        1,
        1882,
        1,
        2140,
        1,
        2177,
        1,
        2193,
        1,
        2196,
        1,
        2211,
        1,
        2226,
        1,
        2262,
        1,
        2279,
        1,
        2300,
        1,
        2307,
        1,
        2311,
        1,
        2316,
        1,
        2319,
        1,
        2322,
        1,
        2326,
        1,
        2330,
        1,
        2336,
        1,
        2344,
        1,
        2349,
        1,
        2362,
        1,
        2370,
        1,
        2401,
        1,
        2402,
        1,
        2405,
        1,
        2412,
        1,
        2417,
        1,
        2427,
        1,
        2434,
        1,
        2438,
        1,
        2450,
        1,
        2451,
        1,
        2460,
        1,
        2466,
        1,
        2468,
        1,
        2469,
        1,
        2497,
        1,
        2508,
        1,
        2539,
        1,
        2544,
        1,
        2556,
        2,
        2557,
        1,
        2559,
        1,
        2561,
        1,
        2562,
        1,
        2563,
        1,
        2566,
        1,
        2567,
        1,
        2568,
        1,
        2569,
        1,
        2570,
        2,
        2571,
        1,
        2572,
        1,
        2573,
        1,
        2575,
        2,
        2577,
        1,
        2579,
        4,
        2581,
        2,
        2582,
        3,
        2583,
        1,
        2584,
        1,
        2586,
        3,
        2587,
        1,
        2588,
        1,
        2589,
        1,
        2590,
        2,
        2591,
        2,
        2592,
        3,
        2593,
        1,
        2594,
        4,
        2595,
        3,
        2597,
        4,
        2598,
        1,
        2599,
        4,
        2600,
        2,
        2601,
        4,
        2602,
        3,
        2603,
        7,
        2606,
        6,
        2607,
        5,
        2608,
        5,
        2609,
        5,
        2610,
        4,
        2611,
        12,
        2612,
        4,
        2613,
        8,
        2614,
        8,
        2615,
        11,
        2616,
        2,
        2617,
        6,
        2618,
        10,
        2619,
        7,
        2620,
        8,
        2621,
        3,
        2622,
        14,
        2623,
        6,
        2624,
        7,
        2625,
        7,
        2626,
        6,
        2627,
        9,
        2628,
        8,
        2629,
        4,
        2630,
        4,
        2631,
        5,
        2632,
        6,
        2633,
        5,
        2634,
        10,
        2635,
        4,
        2636,
        11,
        2637,
        9,
        2638,
        11,
        2639,
        15,
        2640,
        7,
        2641,
        9,
        2642,
        8,
        2643,
        10,
        2644,
        9,
        2645,
        12,
        2646,
        8,
        2647,
        9,
        2648,
        7,
        2649,
        18,
        2650,
        10,
        2651,
        11,
        2652,
        12,
        2653,
        14,
        2654,
        6,
        2655,
        9,
        2656,
        15,
        2657,
        14,
        2658,
        13,
        2659,
        10,
        2660,
        11,
        2661,
        13,
        2662,
        12,
        2663,
        7,
        2664,
        8,
        2665,
        13,
        2666,
        10,
        2667,
        6,
        2668,
        10,
        2669,
        9,
        2670,
        10,
        2671,
        10,
        2672,
        16,
        2673,
        12,
        2674,
        6,
        2675,
        14,
        2676,
        15,
        2677,
        10,
        2678,
        11,
        2679,
        15,
        2680,
        13,
        2681,
        11,
        2682,
        13,
        2683,
        13,
        2684,
        13,
        2685,
        9,
        2686,
        9,
        2687,
        13,
        2688,
        9,
        2689,
        11,
        2690,
        8,
        2691,
        14,
        2692,
        13,
        2693,
        14,
        2694,
        17,
        2695,
        5,
        2696,
        10,
        2697,
        16,
        2698,
        5,
        2699,
        10,
        2700,
        16,
        2701,
        11,
        2702,
        16,
        2703,
        8,
        2704,
        10,
        2705,
        16,
        2706,
        20,
        2707,
        14,
        2708,
        9,
        2709,
        14,
        2710,
        10,
        2711,
        14,
        2712,
        11,
        2713,
        15,
        2714,
        11,
        2715,
        11,
        2716,
        11,
        2717,
        9,
        2718,
        9,
        2719,
        16,
        2720,
        18,
        2721,
        13,
        2722,
        5,
        2723,
        13,
        2724,
        10,
        2725,
        13,
        2726,
        8,
        2727,
        12,
        2728,
        6,
        2729,
        14,
        2730,
        5,
        2731,
        13,
        2732,
        13,
        2733,
        11,
        2734,
        10,
        2735,
        13,
        2736,
        7,
        2737,
        16,
        2738,
        17,
        2739,
        12,
        2740,
        10,
        2741,
        10,
        2742,
        10,
        2743,
        10,
        2744,
        12,
        2745,
        9,
        2746,
        11,
        2747,
        13,
        2748,
        16,
        2749,
        14,
        2750,
        14,
        2751,
        15,
        2752,
        13,
        2753,
        8,
        2754,
        10,
        2755,
        4,
        2756,
        9,
        2757,
        21,
        2758,
        10,
        2759,
        8,
        2760,
        9,
        2761,
        16,
        2762,
        8,
        2763,
        4,
        2764,
        5,
        2765,
        12,
        2766,
        11,
        2767,
        8,
        2768,
        13,
        2769,
        16,
        2770,
        19,
        2771,
        12,
        2772,
        9,
        2773,
        14,
        2774,
        8,
        2775,
        10,
        2776,
        8,
        2777,
        16,
        2778,
        7,
        2779,
        16,
        2780,
        12,
        2781,
        17,
        2782,
        8,
        2783,
        6,
        2784,
        13,
        2785,
        13,
        2786,
        11,
        2787,
        9,
        2788,
        11,
        2789,
        13,
        2790,
        14,
        2791,
        6,
        2792,
        11,
        2793,
        18,
        2794,
        11,
        2795,
        11,
        2796,
        10,
        2797,
        7,
        2798,
        18,
        2799,
        12,
        2800,
        8,
        2801,
        10,
        2802,
        12,
        2803,
        10,
        2804,
        13,
        2805,
        7,
        2806,
        10,
        2807,
        18,
        2808,
        7,
        2809,
        15,
        2810,
        15,
        2811,
        12,
        2812,
        11,
        2813,
        18,
        2814,
        13,
        2815,
        10,
        2816,
        9,
        2817,
        8,
        2818,
        9,
        2819,
        16,
        2820,
        17,
        2821,
        13,
        2822,
        17,
        2823,
        7,
        2824,
        9,
        2825,
        13,
        2826,
        7,
        2827,
        12,
        2828,
        12,
        2829,
        13,
        2830,
        11,
        2831,
        13,
        2832,
        13,
        2833,
        12,
        2834,
        15,
        2835,
        13,
        2836,
        12,
        2837,
        9,
        2838,
        7,
        2839,
        8,
        2840,
        15,
        2841,
        11,
        2842,
        16,
        2843,
        11,
        2844,
        14,
        2845,
        13,
        2846,
        12,
        2847,
        15,
        2848,
        17,
        2849,
        11,
        2850,
        19,
        2851,
        7,
        2852,
        16,
        2853,
        9,
        2854,
        12,
        2855,
        14,
        2856,
        12,
        2857,
        13,
        2858,
        9,
        2859,
        15,
        2860,
        6,
        2861,
        9,
        2862,
        13,
        2863,
        23,
        2864,
        14,
        2865,
        11,
        2866,
        15,
        2867,
        10,
        2868,
        9,
        2869,
        14,
        2870,
        7,
        2871,
        16,
        2872,
        9,
        2873,
        17,
        2874,
        10,
        2875,
        14,
        2876,
        13,
        2877,
        15,
        2878,
        15,
        2879,
        9,
        2880,
        17,
        2881,
        14,
        2882,
        8,
        2883,
        14,
        2884,
        23,
        2885,
        16,
        2886,
        12,
        2887,
        10,
        2888,
        11,
        2889,
        15,
        2890,
        12,
        2891,
        7,
        2892,
        8,
        2893,
        13,
        2894,
        15,
        2895,
        12,
        2896,
        10,
        2897,
        17,
        2898,
        8,
        2899,
        12,
        2900,
        18,
        2901,
        15,
        2902,
        9,
        2903,
        8,
        2904,
        13,
        2905,
        16,
        2906,
        16,
        2907,
        12,
        2908,
        10,
        2909,
        9,
        2910,
        7,
        2911,
        11,
        2912,
        13,
        2913,
        12,
        2914,
        12,
        2915,
        11,
        2916,
        11,
        2917,
        13,
        2918,
        11,
        2919,
        17,
        2920,
        14,
        2921,
        13,
        2922,
        11,
        2923,
        8,
        2924,
        8,
        2925,
        13,
        2926,
        16,
        2927,
        12,
        2928,
        12,
        2929,
        16,
        2930,
        12,
        2931,
        13,
        2932,
        14,
        2933,
        12,
        2934,
        10,
        2935,
        15,
        2936,
        17,
        2937,
        13,
        2938,
        18,
        2939,
        17,
        2940,
        16,
        2941,
        12,
        2942,
        10,
        2943,
        13,
        2944,
        16,
        2945,
        9,
        2946,
        7,
        2947,
        15,
        2948,
        6,
        2949,
        16,
        2950,
        11,
        2951,
        15,
        2952,
        14,
        2953,
        13,
        2954,
        9,
        2955,
        18,
        2956,
        17,
        2957,
        10,
        2958,
        14,
        2959,
        11,
        2960,
        13,
        2961,
        13,
        2962,
        13,
        2963,
        10,
        2964,
        10,
        2965,
        13,
        2966,
        5,
        2967,
        12,
        2968,
        11,
        2969,
        14,
        2970,
        13,
        2971,
        14,
        2972,
        14,
        2973,
        13,
        2974,
        9,
        2975,
        16,
        2976,
        11,
        2977,
        10,
        2978,
        13,
        2979,
        12,
        2980,
        8,
        2981,
        13,
        2982,
        14,
        2983,
        7,
        2984,
        13,
        2985,
        17,
        2986,
        5,
        2987,
        17,
        2988,
        10,
        2989,
        8,
        2990,
        16,
        2991,
        9,
        2992,
        10,
        2993,
        12,
        2994,
        14,
        2995,
        11,
        2996,
        9,
        2997,
        5,
        2998,
        8,
        2999,
        19,
        3000,
        14,
        3001,
        8,
        3002,
        17,
        3003,
        11,
        3004,
        18,
        3005,
        12,
        3006,
        12,
        3007,
        10,
        3008,
        12,
        3009,
        7,
        3010,
        11,
        3011,
        13,
        3012,
        5,
        3013,
        13,
        3014,
        12,
        3015,
        8,
        3016,
        15,
        3017,
        15,
        3018,
        13,
        3019,
        8,
        3020,
        11,
        3021,
        12,
        3022,
        15,
        3023,
        17,
        3024,
        17,
        3025,
        15,
        3026,
        11,
        3027,
        10,
        3028,
        11,
        3029,
        11,
        3030,
        15,
        3031,
        17,
        3032,
        16,
        3033,
        14,
        3034,
        14,
        3035,
        15,
        3036,
        12,
        3037,
        10,
        3038,
        10,
        3039,
        7,
        3040,
        13,
        3041,
        8,
        3042,
        16,
        3043,
        2,
        3044,
        5,
        3045,
        12,
        3046,
        12,
        3047,
        15,
        3048,
        11,
        3049,
        10,
        3050,
        10,
        3051,
        8,
        3052,
        8,
        3053,
        11,
        3054,
        9,
        3055,
        10,
        3056,
        14,
        3057,
        9,
        3058,
        10,
        3059,
        13,
        3060,
        8,
        3061,
        8,
        3062,
        9,
        3063,
        9,
        3064,
        11,
        3065,
        15,
        3066,
        16,
        3067,
        18,
        3068,
        15,
        3069,
        14,
        3070,
        7,
        3071,
        8,
        3072,
        11,
        3073,
        14,
        3074,
        18,
        3075,
        13,
        3076,
        16,
        3077,
        9,
        3078,
        17,
        3079,
        11,
        3080,
        15,
        3081,
        10,
        3082,
        15,
        3083,
        14,
        3084,
        9,
        3085,
        9,
        3086,
        13,
        3087,
        10,
        3088,
        6,
        3089,
        13,
        3090,
        20,
        3091,
        15,
        3092,
        8,
        3093,
        15,
        3094,
        12,
        3095,
        11,
        3096,
        15,
        3097,
        10,
        3098,
        14,
        3099,
        10,
        3100,
        7,
        3101,
        12,
        3102,
        15,
        3103,
        11,
        3104,
        15,
        3105,
        12,
        3106,
        11,
        3107,
        11,
        3108,
        6,
        3109,
        16,
        3110,
        12,
        3111,
        10,
        3112,
        8,
        3113,
        21,
        3114,
        11,
        3115,
        16,
        3116,
        20,
        3117,
        6,
        3118,
        12,
        3119,
        12,
        3120,
        14,
        3121,
        12,
        3122,
        10,
        3123,
        10,
        3124,
        12,
        3125,
        11,
        3126,
        6,
        3127,
        8,
        3128,
        9,
        3129,
        6,
        3130,
        11,
        3131,
        11,
        3132,
        8,
        3133,
        11,
        3134,
        5,
        3135,
        4,
        3136,
        9,
        3137,
        11,
        3138,
        19,
        3139,
        7,
        3140,
        11,
        3141,
        8,
        3142,
        7,
        3143,
        6,
        3144,
        12,
        3145,
        9,
        3146,
        8,
        3147,
        12,
        3148,
        9,
        3149,
        4,
        3150,
        11,
        3151,
        8,
        3152,
        13,
        3153,
        10,
        3154,
        4,
        3155,
        11,
        3156,
        9,
        3157,
        12,
        3158,
        9,
        3159,
        10,
        3160,
        12,
        3161,
        10,
        3162,
        9,
        3163,
        6,
        3164,
        7,
        3165,
        17,
        3166,
        7,
        3167,
        19,
        3168,
        5,
        3169,
        5,
        3170,
        9,
        3171,
        9,
        3172,
        6,
        3173,
        8,
        3174,
        12,
        3175,
        5,
        3176,
        3,
        3177,
        6,
        3178,
        5,
        3179,
        5,
        3180,
        4,
        3181,
        6,
        3182,
        7,
        3183,
        6,
        3184,
        10,
        3185,
        3,
        3186,
        11,
        3187,
        5,
        3188,
        13,
        3189,
        6,
        3190,
        3,
        3191,
        6,
        3192,
        3,
        3193,
        3,
        3194,
        7,
        3195,
        8,
        3196,
        1,
        3197,
        11,
        3198,
        8,
        3199,
        7,
        3200,
        5,
        3201,
        3,
        3202,
        2,
        3203,
        4,
        3204,
        3,
        3205,
        1,
        3206,
        4,
        3207,
        1,
        3208,
        7,
        3209,
        6,
        3210,
        4,
        3211,
        3,
        3212,
        1,
        3213,
        2,
        3214,
        2,
        3215,
        3,
        3216,
        2,
        3217,
        4,
        3218,
        2,
        3219,
        5,
        3220,
        5,
        3221,
        2,
        3222,
        1,
        3224,
        2,
        3225,
        2,
        3226,
        4,
        3227,
        3,
        3228,
        2,
        3229,
        2,
        3231,
        2,
        3232,
        2,
        3233,
        1,
        3234,
        7,
        3235,
        2,
        3237,
        2,
        3239,
        2,
        3241,
        1,
        3242,
        1,
        3243,
        2,
        3244,
        6,
        3245,
        1,
        3247,
        2,
        3249,
        1,
        3250,
        1,
        3251,
        3,
        3252,
        1,
        3253,
        1,
        3254,
        4,
        3255,
        2,
        3257,
        1,
        3260,
        1,
        3261,
        1,
        3262,
        2,
        3263,
        2,
        3264,
        3,
        3265,
        1,
        3266,
        4,
        3267,
        2,
        3268,
        3,
        3269,
        2,
        3270,
        2,
        3271,
        2,
        3272,
        2,
        3273,
        1,
        3274,
        4,
        3275,
        4,
        3276,
        1,
        3277,
        1,
        3278,
        1,
        3279,
        1,
        3281,
        2,
        3282,
        5,
        3283,
        1,
        3284,
        5,
        3285,
        2,
        3286,
        3,
        3287,
        3,
        3288,
        1,
        3289,
        4,
        3290,
        1,
        3291,
        3,
        3292,
        1,
        3293,
        2,
        3294,
        1,
        3295,
        3,
        3296,
        1,
        3297,
        3,
        3298,
        1,
        3299,
        1,
        3300,
        2,
        3302,
        1,
        3303,
        2,
        3304,
        3,
        3305,
        2,
        3306,
        3,
        3308,
        2,
        3309,
        2,
        3310,
        1,
        3311,
        1,
        3312,
        1,
        3313,
        3,
        3315,
        2,
        3316,
        1,
        3317,
        1,
        3318,
        3,
        3319,
        2,
        3320,
        3,
        3321,
        3,
        3322,
        5,
        3323,
        4,
        3324,
        3,
        3325,
        4,
        3327,
        3,
        3328,
        3,
        3329,
        3,
        3331,
        3,
        3332,
        2,
        3333,
        1,
        3334,
        4,
        3335,
        1,
        3336,
        3,
        3337,
        2,
        3338,
        1,
        3339,
        4,
        3340,
        1,
        3341,
        4,
        3342,
        2,
        3343,
        2,
        3344,
        1,
        3346,
        2,
        3347,
        5,
        3348,
        3,
        3349,
        2,
        3350,
        1,
        3351,
        7,
        3353,
        3,
        3354,
        1,
        3355,
        1,
        3356,
        2,
        3358,
        1,
        3359,
        2,
        3360,
        1,
        3361,
        2,
        3362,
        3,
        3364,
        3,
        3365,
        1,
        3366,
        1,
        3367,
        1,
        3368,
        3,
        3369,
        3,
        3370,
        1,
        3371,
        3,
        3372,
        2,
        3373,
        1,
        3375,
        2,
        3377,
        3,
        3378,
        1,
        3379,
        2,
        3381,
        1,
        3383,
        2,
        3384,
        1,
        3387,
        1,
        3388,
        1,
        3398,
        1,
        3400,
        1,
        3401,
        1,
        3402,
        1,
        3403,
        1,
        3407,
        1,
        3416,
        1,
        3421,
        1,
        3422,
        1,
        3430,
        1,
        3432,
        1,
        3460,
        1,
        3463,
        1,
        3467,
        1,
        3476,
        1,
        3490,
        1,
        3497,
        1,
        3504,
        1,
        3505,
        1,
        3507,
        1,
        3518,
        1,
        3548,
        1,
        3562,
        1,
        3564,
        1,
        3567,
        1,
        3574,
        1,
        3578,
        1,
        3579,
        1,
        3590,
        1,
        3716,
        1,
        3731,
        1,
        3755,
        1,
        3780,
        1,
        3785,
        1,
        3798,
        2,
        3974,
        1,
        4097,
        1,
        4122,
        1,
        4205,
        1,
        4264,
        1,
        4408,
        1,
        6334,
        1,
        6383,
        1,
        6474,
        1,
        6497,
        1,
        6500,
        1,
        6511,
        1,
        6519,
        1,
        6534,
        1,
        6554,
        1,
        6555,
        1,
        6566,
        1,
        6579,
        1,
        6585,
        1,
        6617,
        1,
        6717,
        1,
        7223,
        1,
        7363,
        1,
        7403,
        1,
        7570,
        1,
        7614,
        1,
        7912,
        1,
        8035,
        1,
        8060,
        1,
        8143,
        1,
        8202,
        1,
        8346,
        1
      ],
      "req_per_sec": [
        808,
        2,
        828,
        1,
        830,
        1,
        848,
        2,
        868,
        1,
        870,
        2,
        878,
        1,
        880,
        1,
        890,
        1,
        900,
        1,
        910,
        1,
        929,
        2,
        930,
        1,
        970,
        1,
        980,
        1,
        990,
        1,
        1000,
        2,
        1020,
        1,
        1029,
        1,
        1030,
        2,
        1100,
        1,
        1101,
        1,
        1110,
        1,
        1111,
        2,
        1131,
        1,
        1140,
        1,
        1141,
        1,
        1170,
        2,
        1181,
        1,
        1191,
        1,
        1202,
        2,
        1210,
        1,
        1230,
        1,
        1232,
        2,
        1240,
        107,
        1242,
        15,
        1247,
        1,
        1250,
        374,
        1252,
        313,
        1260,
        297,
        1262,
        256,
        1267,
        1,
        1270,
        300,
        1272,
        356,
        1280,
        597,
        1282,
        648,
        1290,
        503,
        1292,
        191,
        1300,
        169,
        1303,
        228,
        1310,
        119,
        1313,
        202,
        1320,
        35,
        1323,
        41,
        1330,
        2,
        1333,
        1
      ],
      "errors": {
        "connect": 0,
        "read": 0,
        "write": 0,
        "status": 0,
        "timeout": 0
      }
    }
  }
}